Lab3/lab3_add.v
module full_adder(sum, cout, a, b, cin);
  input a,b,cin;
  output sum,cout;
  wire d,e,f;

  xor #4 U1(sum,a,b,cin);
  
  and #1U2(d,a,b);
  
  and #1U3(e,b,cin);
  
  and #1U4(f,a,cin);
 
  or #2U5(cout,d,e,f);
 
  
endmodule

module add16_rc(sum16, cout, a16, b16, cin);
  input [15:0]a16, b16;
  output [15:0] sum16;
  input cin;
  output cout;
  wire z1,z2,z3,z4,z5,z6,z7,z8,z9,z10,z11,z12,z13,z14,z15;
  full_adder U6(sum16[0], z1, a16[0], b16[0], cin);
  full_adder U7(sum16[1], z2, a16[1], b16[1], z1);
  full_adder U8(sum16[2], z3, a16[2], b16[2], z2);
  full_adder U9(sum16[3], z4, a16[3], b16[3], z3);
  full_adder U10(sum16[4], z5, a16[4], b16[4], z4);
  full_adder U11(sum16[5], z6, a16[5], b16[5], z5);
  full_adder U12(sum16[6], z7, a16[6], b16[6], z6);
  full_adder U13(sum16[7], z8, a16[7], b16[7], z7);
  full_adder U14(sum16[8], z9, a16[8], b16[8], z8);
  full_adder U15(sum16[9], z10, a16[9], b16[9], z9);
  full_adder U16(sum16[10], z11, a16[10], b16[10], z10);
  full_adder U17(sum16[11], z12, a16[11], b16[11], z11);
  full_adder U18(sum16[12], z13, a16[12], b16[12], z12);
  full_adder U19(sum16[13], z14, a16[13], b16[13], z13);
  full_adder U20(sum16[14], z15, a16[14], b16[14], z14);
  full_adder U21(sum16[15], cout, a16[15], b16[15], z15);
    
endmodule

module full_adder_pg(p,g, a, b);
  input a,b;
  output p,g;
  
  or #1 U6(p,a,b);
  and #1 U7(g,a,b);
 		
  
endmodule


module carry_generator(couts, p, g, cin);
  input cin;
  input [3:0] p,g;
  output [3:0] couts;
  wire s1,s2,s3,s4;
  
  and #1Y1(s1,p[0],cin);
  
  or #1Y2(couts[0],s1,g[0]);
  
  and #1Y3(s2,p[1],couts[0]);
  
  or #1Y4(couts[1],s2,g[1]);
  
  and #1Y5(s3,p[2],couts[1]);
  
  or #1Y6(couts[2],s3,g[2]);
  
  and #1Y7(s4,p[3],couts[2]);
  
  or #1Y8(couts[3],s4,g[3]);
  
	  
endmodule

module add4_cla(sum4, cout, a4, b4, cin);
  input[3:0] a4,b4;
  output[3:0] sum4;
  input cin;
  output cout;
  wire[3:0] p,g,couts;
  wire t1,t2,t3,t4,t5,t6,t7,t8;
 
  full_adder_pg J1(p[0],g[0], a4[0], b4[0]);
  full_adder_pg J2(p[1],g[1], a4[1], b4[1]);
  full_adder_pg J3(p[2],g[2], a4[2], b4[2]);
  full_adder_pg J4(p[3],g[3], a4[3], b4[3]);
  carry_generator tyu(couts,p,g,cin);
  
  full_adder J5(sum4[0], t5, a4[0], b4[0], cin);
  full_adder J6(sum4[1], t6, a4[1], b4[1], couts[0]);
  full_adder J7(sum4[2], t7, a4[2], b4[2], couts[1]);
  full_adder J8(sum4[3], t8, a4[3], b4[3], couts[2]);
  assign cout=couts[3];
  
endmodule



module add16_cla(sum16, cout, a16, b16, cin);
  input[15:0] a16, b16;
  output[15:0] sum16;
  output cout;
  input cin;
  wire e1,e2,e3;
  
  add4_cla bla1(sum16[3:0], e1, a16[3:0], b16[3:0], cin);
  add4_cla bla2(sum16[7:4], e2, a16[7:4], b16[7:4], e1);
  add4_cla bla3(sum16[11:8], e3, a16[11:8], b16[11:8], e2);
  add4_cla bla4(sum16[15:12], cout, a16[15:12], b16[15:12], e3);
 
endmodule

Lab3/testbench.v
module rc_tb();
  reg[15:0] ra16,rb16;
  reg rcin;
  wire wcout,w1cout;
  wire[15:0] wsum16,w1sum16;
  
  add16_rc rc_ins(.sum16(wsum16), .cout(wcout), .a16(ra16), .b16(rb16), .cin(rcin));
  add16_cla cla_ins(.sum16(w1sum16), .cout(w1cout), .a16(ra16), .b16(rb16), .cin(rcin));
  
  initial
    begin
      ra16=16'b1111111111111111; rb16=16'b0000000010001000; rcin=1'b0;
      #50
      $display("a16: %b,b16: %b,sum16_ripple carry adder: %b, sum16_cla: %b",ra16,rb16,wsum16,w1sum16);
      
      ra16=16'b1001111111111111; rb16=16'b1000000010001000;rcin=1'b0;
      #50
      $display("a16: %b,b16: %b,sum16_ripple carry adder: %b, sum16_cla: %b",ra16,rb16,wsum16,w1sum16);
      
      ra16=16'b1111001111111111; rb16=16'b1000000010001000;rcin=1'b0;
      #50
      $display("a16: %b,b16: %b,sum16_ripple carry adder: %b, sum16_cla: %b",ra16,rb16,wsum16,w1sum16);
      
      ra16=16'b1111111111100111; rb16=16'b1000000010001000;rcin=1'b0;
      #50
      $display("a16: %b,b16: %b,sum16_ripple carry adder: %b, sum16_cla: %b",ra16,rb16,wsum16,w1sum16);
      
    end
  initial
    begin
      $dumpfile("2019csb1100.vcd");
      $dumpvars;
      
    end
 
endmodule

Lab3/2019csb1100.vcd
$date
	Tue Oct 06 23:09:13 2020
$end
$version
	Icarus Verilog
$end
$timescale
	1s
$end
$scope module rc_tb $end
$var wire 16 ! wsum16 [15:0] $end
$var wire 1 " wcout $end
$var wire 16 # w1sum16 [15:0] $end
$var wire 1 $ w1cout $end
$var reg 16 % ra16 [15:0] $end
$var reg 16 & rb16 [15:0] $end
$var reg 1 ' rcin $end
$scope module cla_ins $end
$var wire 16 ( a16 [15:0] $end
$var wire 16 ) b16 [15:0] $end
$var wire 1 ' cin $end
$var wire 16 * sum16 [15:0] $end
$var wire 1 + e3 $end
$var wire 1 , e2 $end
$var wire 1 - e1 $end
$var wire 1 $ cout $end
$scope module bla1 $end
$var wire 4 . a4 [3:0] $end
$var wire 4 / b4 [3:0] $end
$var wire 1 ' cin $end
$var wire 1 0 t8 $end
$var wire 1 1 t7 $end
$var wire 1 2 t6 $end
$var wire 1 3 t5 $end
$var wire 4 4 sum4 [3:0] $end
$var wire 4 5 p [3:0] $end
$var wire 4 6 g [3:0] $end
$var wire 4 7 couts [3:0] $end
$var wire 1 - cout $end
$scope module J1 $end
$var wire 1 8 a $end
$var wire 1 9 b $end
$var wire 1 : g $end
$var wire 1 ; p $end
$upscope $end
$scope module J2 $end
$var wire 1 < a $end
$var wire 1 = b $end
$var wire 1 > g $end
$var wire 1 ? p $end
$upscope $end
$scope module J3 $end
$var wire 1 @ a $end
$var wire 1 A b $end
$var wire 1 B g $end
$var wire 1 C p $end
$upscope $end
$scope module J4 $end
$var wire 1 D a $end
$var wire 1 E b $end
$var wire 1 F g $end
$var wire 1 G p $end
$upscope $end
$scope module J5 $end
$var wire 1 H a $end
$var wire 1 I b $end
$var wire 1 ' cin $end
$var wire 1 3 cout $end
$var wire 1 J d $end
$var wire 1 K e $end
$var wire 1 L f $end
$var wire 1 M sum $end
$upscope $end
$scope module J6 $end
$var wire 1 N a $end
$var wire 1 O b $end
$var wire 1 P cin $end
$var wire 1 2 cout $end
$var wire 1 Q d $end
$var wire 1 R e $end
$var wire 1 S f $end
$var wire 1 T sum $end
$upscope $end
$scope module J7 $end
$var wire 1 U a $end
$var wire 1 V b $end
$var wire 1 W cin $end
$var wire 1 1 cout $end
$var wire 1 X d $end
$var wire 1 Y e $end
$var wire 1 Z f $end
$var wire 1 [ sum $end
$upscope $end
$scope module J8 $end
$var wire 1 \ a $end
$var wire 1 ] b $end
$var wire 1 ^ cin $end
$var wire 1 0 cout $end
$var wire 1 _ d $end
$var wire 1 ` e $end
$var wire 1 a f $end
$var wire 1 b sum $end
$upscope $end
$scope module tyu $end
$var wire 1 ' cin $end
$var wire 4 c g [3:0] $end
$var wire 4 d p [3:0] $end
$var wire 1 e s1 $end
$var wire 1 f s2 $end
$var wire 1 g s3 $end
$var wire 1 h s4 $end
$var wire 4 i couts [3:0] $end
$upscope $end
$upscope $end
$scope module bla2 $end
$var wire 4 j a4 [3:0] $end
$var wire 4 k b4 [3:0] $end
$var wire 1 - cin $end
$var wire 1 l t8 $end
$var wire 1 m t7 $end
$var wire 1 n t6 $end
$var wire 1 o t5 $end
$var wire 4 p sum4 [3:0] $end
$var wire 4 q p [3:0] $end
$var wire 4 r g [3:0] $end
$var wire 4 s couts [3:0] $end
$var wire 1 , cout $end
$scope module J1 $end
$var wire 1 t a $end
$var wire 1 u b $end
$var wire 1 v g $end
$var wire 1 w p $end
$upscope $end
$scope module J2 $end
$var wire 1 x a $end
$var wire 1 y b $end
$var wire 1 z g $end
$var wire 1 { p $end
$upscope $end
$scope module J3 $end
$var wire 1 | a $end
$var wire 1 } b $end
$var wire 1 ~ g $end
$var wire 1 !" p $end
$upscope $end
$scope module J4 $end
$var wire 1 "" a $end
$var wire 1 #" b $end
$var wire 1 $" g $end
$var wire 1 %" p $end
$upscope $end
$scope module J5 $end
$var wire 1 &" a $end
$var wire 1 '" b $end
$var wire 1 - cin $end
$var wire 1 o cout $end
$var wire 1 (" d $end
$var wire 1 )" e $end
$var wire 1 *" f $end
$var wire 1 +" sum $end
$upscope $end
$scope module J6 $end
$var wire 1 ," a $end
$var wire 1 -" b $end
$var wire 1 ." cin $end
$var wire 1 n cout $end
$var wire 1 /" d $end
$var wire 1 0" e $end
$var wire 1 1" f $end
$var wire 1 2" sum $end
$upscope $end
$scope module J7 $end
$var wire 1 3" a $end
$var wire 1 4" b $end
$var wire 1 5" cin $end
$var wire 1 m cout $end
$var wire 1 6" d $end
$var wire 1 7" e $end
$var wire 1 8" f $end
$var wire 1 9" sum $end
$upscope $end
$scope module J8 $end
$var wire 1 :" a $end
$var wire 1 ;" b $end
$var wire 1 <" cin $end
$var wire 1 l cout $end
$var wire 1 =" d $end
$var wire 1 >" e $end
$var wire 1 ?" f $end
$var wire 1 @" sum $end
$upscope $end
$scope module tyu $end
$var wire 1 - cin $end
$var wire 4 A" g [3:0] $end
$var wire 4 B" p [3:0] $end
$var wire 1 C" s1 $end
$var wire 1 D" s2 $end
$var wire 1 E" s3 $end
$var wire 1 F" s4 $end
$var wire 4 G" couts [3:0] $end
$upscope $end
$upscope $end
$scope module bla3 $end
$var wire 4 H" a4 [3:0] $end
$var wire 4 I" b4 [3:0] $end
$var wire 1 , cin $end
$var wire 1 J" t8 $end
$var wire 1 K" t7 $end
$var wire 1 L" t6 $end
$var wire 1 M" t5 $end
$var wire 4 N" sum4 [3:0] $end
$var wire 4 O" p [3:0] $end
$var wire 4 P" g [3:0] $end
$var wire 4 Q" couts [3:0] $end
$var wire 1 + cout $end
$scope module J1 $end
$var wire 1 R" a $end
$var wire 1 S" b $end
$var wire 1 T" g $end
$var wire 1 U" p $end
$upscope $end
$scope module J2 $end
$var wire 1 V" a $end
$var wire 1 W" b $end
$var wire 1 X" g $end
$var wire 1 Y" p $end
$upscope $end
$scope module J3 $end
$var wire 1 Z" a $end
$var wire 1 [" b $end
$var wire 1 \" g $end
$var wire 1 ]" p $end
$upscope $end
$scope module J4 $end
$var wire 1 ^" a $end
$var wire 1 _" b $end
$var wire 1 `" g $end
$var wire 1 a" p $end
$upscope $end
$scope module J5 $end
$var wire 1 b" a $end
$var wire 1 c" b $end
$var wire 1 , cin $end
$var wire 1 M" cout $end
$var wire 1 d" d $end
$var wire 1 e" e $end
$var wire 1 f" f $end
$var wire 1 g" sum $end
$upscope $end
$scope module J6 $end
$var wire 1 h" a $end
$var wire 1 i" b $end
$var wire 1 j" cin $end
$var wire 1 L" cout $end
$var wire 1 k" d $end
$var wire 1 l" e $end
$var wire 1 m" f $end
$var wire 1 n" sum $end
$upscope $end
$scope module J7 $end
$var wire 1 o" a $end
$var wire 1 p" b $end
$var wire 1 q" cin $end
$var wire 1 K" cout $end
$var wire 1 r" d $end
$var wire 1 s" e $end
$var wire 1 t" f $end
$var wire 1 u" sum $end
$upscope $end
$scope module J8 $end
$var wire 1 v" a $end
$var wire 1 w" b $end
$var wire 1 x" cin $end
$var wire 1 J" cout $end
$var wire 1 y" d $end
$var wire 1 z" e $end
$var wire 1 {" f $end
$var wire 1 |" sum $end
$upscope $end
$scope module tyu $end
$var wire 1 , cin $end
$var wire 4 }" g [3:0] $end
$var wire 4 ~" p [3:0] $end
$var wire 1 !# s1 $end
$var wire 1 "# s2 $end
$var wire 1 ## s3 $end
$var wire 1 $# s4 $end
$var wire 4 %# couts [3:0] $end
$upscope $end
$upscope $end
$scope module bla4 $end
$var wire 4 &# a4 [3:0] $end
$var wire 4 '# b4 [3:0] $end
$var wire 1 + cin $end
$var wire 1 (# t8 $end
$var wire 1 )# t7 $end
$var wire 1 *# t6 $end
$var wire 1 +# t5 $end
$var wire 4 ,# sum4 [3:0] $end
$var wire 4 -# p [3:0] $end
$var wire 4 .# g [3:0] $end
$var wire 4 /# couts [3:0] $end
$var wire 1 $ cout $end
$scope module J1 $end
$var wire 1 0# a $end
$var wire 1 1# b $end
$var wire 1 2# g $end
$var wire 1 3# p $end
$upscope $end
$scope module J2 $end
$var wire 1 4# a $end
$var wire 1 5# b $end
$var wire 1 6# g $end
$var wire 1 7# p $end
$upscope $end
$scope module J3 $end
$var wire 1 8# a $end
$var wire 1 9# b $end
$var wire 1 :# g $end
$var wire 1 ;# p $end
$upscope $end
$scope module J4 $end
$var wire 1 <# a $end
$var wire 1 =# b $end
$var wire 1 ># g $end
$var wire 1 ?# p $end
$upscope $end
$scope module J5 $end
$var wire 1 @# a $end
$var wire 1 A# b $end
$var wire 1 + cin $end
$var wire 1 +# cout $end
$var wire 1 B# d $end
$var wire 1 C# e $end
$var wire 1 D# f $end
$var wire 1 E# sum $end
$upscope $end
$scope module J6 $end
$var wire 1 F# a $end
$var wire 1 G# b $end
$var wire 1 H# cin $end
$var wire 1 *# cout $end
$var wire 1 I# d $end
$var wire 1 J# e $end
$var wire 1 K# f $end
$var wire 1 L# sum $end
$upscope $end
$scope module J7 $end
$var wire 1 M# a $end
$var wire 1 N# b $end
$var wire 1 O# cin $end
$var wire 1 )# cout $end
$var wire 1 P# d $end
$var wire 1 Q# e $end
$var wire 1 R# f $end
$var wire 1 S# sum $end
$upscope $end
$scope module J8 $end
$var wire 1 T# a $end
$var wire 1 U# b $end
$var wire 1 V# cin $end
$var wire 1 (# cout $end
$var wire 1 W# d $end
$var wire 1 X# e $end
$var wire 1 Y# f $end
$var wire 1 Z# sum $end
$upscope $end
$scope module tyu $end
$var wire 1 + cin $end
$var wire 4 [# g [3:0] $end
$var wire 4 \# p [3:0] $end
$var wire 1 ]# s1 $end
$var wire 1 ^# s2 $end
$var wire 1 _# s3 $end
$var wire 1 `# s4 $end
$var wire 4 a# couts [3:0] $end
$upscope $end
$upscope $end
$upscope $end
$scope module rc_ins $end
$var wire 16 b# a16 [15:0] $end
$var wire 16 c# b16 [15:0] $end
$var wire 1 ' cin $end
$var wire 1 d# z9 $end
$var wire 1 e# z8 $end
$var wire 1 f# z7 $end
$var wire 1 g# z6 $end
$var wire 1 h# z5 $end
$var wire 1 i# z4 $end
$var wire 1 j# z3 $end
$var wire 1 k# z2 $end
$var wire 1 l# z15 $end
$var wire 1 m# z14 $end
$var wire 1 n# z13 $end
$var wire 1 o# z12 $end
$var wire 1 p# z11 $end
$var wire 1 q# z10 $end
$var wire 1 r# z1 $end
$var wire 16 s# sum16 [15:0] $end
$var wire 1 " cout $end
$scope module U10 $end
$var wire 1 t# a $end
$var wire 1 u# b $end
$var wire 1 h# cout $end
$var wire 1 v# d $end
$var wire 1 w# e $end
$var wire 1 x# f $end
$var wire 1 y# sum $end
$var wire 1 i# cin $end
$upscope $end
$scope module U11 $end
$var wire 1 z# a $end
$var wire 1 {# b $end
$var wire 1 h# cin $end
$var wire 1 g# cout $end
$var wire 1 |# d $end
$var wire 1 }# e $end
$var wire 1 ~# f $end
$var wire 1 !$ sum $end
$upscope $end
$scope module U12 $end
$var wire 1 "$ a $end
$var wire 1 #$ b $end
$var wire 1 g# cin $end
$var wire 1 f# cout $end
$var wire 1 $$ d $end
$var wire 1 %$ e $end
$var wire 1 &$ f $end
$var wire 1 '$ sum $end
$upscope $end
$scope module U13 $end
$var wire 1 ($ a $end
$var wire 1 )$ b $end
$var wire 1 f# cin $end
$var wire 1 e# cout $end
$var wire 1 *$ d $end
$var wire 1 +$ e $end
$var wire 1 ,$ f $end
$var wire 1 -$ sum $end
$upscope $end
$scope module U14 $end
$var wire 1 .$ a $end
$var wire 1 /$ b $end
$var wire 1 e# cin $end
$var wire 1 d# cout $end
$var wire 1 0$ d $end
$var wire 1 1$ e $end
$var wire 1 2$ f $end
$var wire 1 3$ sum $end
$upscope $end
$scope module U15 $end
$var wire 1 4$ a $end
$var wire 1 5$ b $end
$var wire 1 d# cin $end
$var wire 1 q# cout $end
$var wire 1 6$ d $end
$var wire 1 7$ e $end
$var wire 1 8$ f $end
$var wire 1 9$ sum $end
$upscope $end
$scope module U16 $end
$var wire 1 :$ a $end
$var wire 1 ;$ b $end
$var wire 1 q# cin $end
$var wire 1 p# cout $end
$var wire 1 <$ d $end
$var wire 1 =$ e $end
$var wire 1 >$ f $end
$var wire 1 ?$ sum $end
$upscope $end
$scope module U17 $end
$var wire 1 @$ a $end
$var wire 1 A$ b $end
$var wire 1 p# cin $end
$var wire 1 o# cout $end
$var wire 1 B$ d $end
$var wire 1 C$ e $end
$var wire 1 D$ f $end
$var wire 1 E$ sum $end
$upscope $end
$scope module U18 $end
$var wire 1 F$ a $end
$var wire 1 G$ b $end
$var wire 1 o# cin $end
$var wire 1 n# cout $end
$var wire 1 H$ d $end
$var wire 1 I$ e $end
$var wire 1 J$ f $end
$var wire 1 K$ sum $end
$upscope $end
$scope module U19 $end
$var wire 1 L$ a $end
$var wire 1 M$ b $end
$var wire 1 n# cin $end
$var wire 1 m# cout $end
$var wire 1 N$ d $end
$var wire 1 O$ e $end
$var wire 1 P$ f $end
$var wire 1 Q$ sum $end
$upscope $end
$scope module U20 $end
$var wire 1 R$ a $end
$var wire 1 S$ b $end
$var wire 1 m# cin $end
$var wire 1 l# cout $end
$var wire 1 T$ d $end
$var wire 1 U$ e $end
$var wire 1 V$ f $end
$var wire 1 W$ sum $end
$upscope $end
$scope module U21 $end
$var wire 1 X$ a $end
$var wire 1 Y$ b $end
$var wire 1 l# cin $end
$var wire 1 " cout $end
$var wire 1 Z$ d $end
$var wire 1 [$ e $end
$var wire 1 \$ f $end
$var wire 1 ]$ sum $end
$upscope $end
$scope module U6 $end
$var wire 1 ^$ a $end
$var wire 1 _$ b $end
$var wire 1 ' cin $end
$var wire 1 r# cout $end
$var wire 1 `$ d $end
$var wire 1 a$ e $end
$var wire 1 b$ f $end
$var wire 1 c$ sum $end
$upscope $end
$scope module U7 $end
$var wire 1 d$ a $end
$var wire 1 e$ b $end
$var wire 1 r# cin $end
$var wire 1 k# cout $end
$var wire 1 f$ d $end
$var wire 1 g$ e $end
$var wire 1 h$ f $end
$var wire 1 i$ sum $end
$upscope $end
$scope module U8 $end
$var wire 1 j$ a $end
$var wire 1 k$ b $end
$var wire 1 k# cin $end
$var wire 1 j# cout $end
$var wire 1 l$ d $end
$var wire 1 m$ e $end
$var wire 1 n$ f $end
$var wire 1 o$ sum $end
$upscope $end
$scope module U9 $end
$var wire 1 p$ a $end
$var wire 1 q$ b $end
$var wire 1 j# cin $end
$var wire 1 i# cout $end
$var wire 1 r$ d $end
$var wire 1 s$ e $end
$var wire 1 t$ f $end
$var wire 1 u$ sum $end
$upscope $end
$upscope $end
$upscope $end
$enddefinitions $end
#0
$dumpvars
xu$
xt$
xs$
xr$
1q$
1p$
xo$
xn$
xm$
xl$
0k$
1j$
xi$
xh$
xg$
xf$
0e$
1d$
xc$
xb$
xa$
x`$
0_$
1^$
x]$
x\$
x[$
xZ$
0Y$
1X$
xW$
xV$
xU$
xT$
0S$
1R$
xQ$
xP$
xO$
xN$
0M$
1L$
xK$
xJ$
xI$
xH$
0G$
1F$
xE$
xD$
xC$
xB$
0A$
1@$
x?$
x>$
x=$
x<$
0;$
1:$
x9$
x8$
x7$
x6$
05$
14$
x3$
x2$
x1$
x0$
0/$
1.$
x-$
x,$
x+$
x*$
1)$
1($
x'$
x&$
x%$
x$$
0#$
1"$
x!$
x~#
x}#
x|#
0{#
1z#
xy#
xx#
xw#
xv#
0u#
1t#
bx s#
xr#
xq#
xp#
xo#
xn#
xm#
xl#
xk#
xj#
xi#
xh#
xg#
xf#
xe#
xd#
b10001000 c#
b1111111111111111 b#
bx a#
x`#
x_#
x^#
x]#
bx \#
bx [#
xZ#
xY#
xX#
xW#
xV#
0U#
1T#
xS#
xR#
xQ#
xP#
xO#
0N#
1M#
xL#
xK#
xJ#
xI#
xH#
0G#
1F#
xE#
xD#
xC#
xB#
0A#
1@#
x?#
x>#
0=#
1<#
x;#
x:#
09#
18#
x7#
x6#
05#
14#
x3#
x2#
01#
10#
bx /#
bx .#
bx -#
bx ,#
x+#
x*#
x)#
x(#
b0 '#
b1111 &#
bx %#
x$#
x##
x"#
x!#
bx ~"
bx }"
x|"
x{"
xz"
xy"
xx"
0w"
1v"
xu"
xt"
xs"
xr"
xq"
0p"
1o"
xn"
xm"
xl"
xk"
xj"
0i"
1h"
xg"
xf"
xe"
xd"
0c"
1b"
xa"
x`"
0_"
1^"
x]"
x\"
0["
1Z"
xY"
xX"
0W"
1V"
xU"
xT"
0S"
1R"
bx Q"
bx P"
bx O"
bx N"
xM"
xL"
xK"
xJ"
b0 I"
b1111 H"
bx G"
xF"
xE"
xD"
xC"
bx B"
bx A"
x@"
x?"
x>"
x="
x<"
1;"
1:"
x9"
x8"
x7"
x6"
x5"
04"
13"
x2"
x1"
x0"
x/"
x."
0-"
1,"
x+"
x*"
x)"
x("
0'"
1&"
x%"
x$"
1#"
1""
x!"
x~
0}
1|
x{
xz
0y
1x
xw
xv
0u
1t
bx s
bx r
bx q
bx p
xo
xn
xm
xl
b1000 k
b1111 j
bx i
xh
xg
xf
xe
bx d
bx c
xb
xa
x`
x_
x^
1]
1\
x[
xZ
xY
xX
xW
0V
1U
xT
xS
xR
xQ
xP
0O
1N
xM
xL
xK
xJ
0I
1H
xG
xF
1E
1D
xC
xB
0A
1@
x?
x>
0=
1<
x;
x:
09
18
bx 7
bx 6
bx 5
bx 4
x3
x2
x1
x0
b1000 /
b1111 .
x-
x,
x+
bx *
b10001000 )
b1111111111111111 (
0'
b10001000 &
b1111111111111111 %
x$
bx #
x"
bx !
$end
#1
0R
0Y
0)"
00"
07"
0e"
0l"
0s"
0z"
0C#
0J#
0Q#
0X#
1;
0:
1?
0>
1C
0B
b1111 5
b1111 d
1G
b1000 6
b1000 c
1F
0J
0Q
0X
1_
1w
0v
1{
0z
1!"
0~
b1111 q
b1111 B"
1%"
b1000 r
b1000 A"
1$"
0("
0/"
06"
1="
1U"
0T"
1Y"
0X"
1]"
0\"
b1111 O"
b1111 ~"
1a"
b0 P"
b0 }"
0`"
0d"
0k"
0r"
0y"
13#
02#
17#
06#
1;#
0:#
b1111 -#
b1111 \#
1?#
b0 .#
b0 [#
0>#
0B#
0I#
0P#
0W#
0g$
0m$
0w#
0}#
0%$
01$
07$
0=$
0C$
0I$
0O$
0U$
0[$
0`$
0f$
0l$
1r$
0v#
0|#
0$$
1*$
00$
06$
0<$
0B$
0H$
0N$
0T$
0Z$
0b$
0a$
0e
0L
0K
#2
0P
1-
1,
b1xx0 7
b1xx0 i
b1xxx s
b1xxx G"
#3
0f
0S
1*"
1C"
1f"
1!#
10
1l
1i#
1e#
0r#
03
#4
0W
1."
1j"
b1x00 7
b1x00 i
b1xx1 s
b1xx1 G"
bx1 Q"
bx1 %#
1x#
12$
0h$
bx1 #
bx1 *
bx1 4
1M
bx1 !
bx1 s#
1c$
#5
0g
0Z
1D"
11"
1"#
1m"
02
1o
1M"
#6
0^
15"
1q"
b1000 7
b1000 i
b1x11 s
b1x11 G"
bx11 Q"
bx11 %#
1h#
1d#
0k#
bx11 4
1T
bx0 p
0+"
bx0xxx0xx11 #
bx0xxx0xx11 *
bx0 N"
0g"
#7
0h
0`
0a
1E"
18"
1##
1t"
1~#
18$
0n$
01
1n
1L"
0y#
03$
bx0xxx0xx11 !
bx0xxx0xx11 s#
1i$
#8
1<"
1x"
b1111 s
b1111 G"
bx111 Q"
bx111 %#
bx111 4
1[
bx00 p
02"
bx00xx00x111 #
bx00xx00x111 *
bx00 N"
0n"
#9
1F"
1>"
1?"
1$#
1{"
1m
1K"
1g#
1q#
0j#
#10
1+
b1111 Q"
b1111 %#
1&$
1>$
0s$
0t$
b111 4
0b
bx000 p
09"
bx000x0000111 #
bx000x0000111 *
bx000 N"
0u"
0!$
09$
bx00xx00x111 !
bx00xx00x111 s#
1o$
#11
1D#
1]#
1J"
#12
1H#
bx1 /#
bx1 a#
1f#
1p#
b1000 p
1@"
bx000010000111 #
bx000010000111 *
b0 N"
0|"
#13
1^#
1K#
1+$
1,$
1D$
1+#
0'$
0?$
bx000x0000111 !
bx000x0000111 s#
0u$
#14
1O#
bx11 /#
bx11 a#
bx0000010000111 #
bx0000010000111 *
bx0 ,#
0E#
#15
1_#
1R#
1*#
1o#
#16
1V#
bx111 /#
bx111 a#
1J$
bx00000010000111 #
bx00000010000111 *
bx00 ,#
0L#
1-$
bx000010000111 !
bx000010000111 s#
0E$
#17
1`#
1Y#
1)#
#18
1$
b1111 /#
b1111 a#
1n#
bx000000010000111 #
bx000000010000111 *
bx000 ,#
0S#
#19
1P$
1(#
bx0000010000111 !
bx0000010000111 s#
0K$
#20
b10000111 #
b10000111 *
b0 ,#
0Z#
#21
1m#
#22
1V$
bx00000010000111 !
bx00000010000111 s#
0Q$
#24
1l#
#25
1\$
bx000000010000111 !
bx000000010000111 s#
0W$
#27
1"
#28
b10000111 !
b10000111 s#
0]$
#50
1=#
1U#
04#
08#
0F#
0M#
b1000 '#
1Y$
b1001 &#
0L$
0R$
b1000000010001000 &
b1000000010001000 )
b1000000010001000 c#
b1001111111111111 %
b1001111111111111 (
b1001111111111111 b#
#51
b1000 .#
b1000 [#
1>#
1W#
1X#
07#
b1001 -#
b1001 \#
0;#
0K#
0R#
1Z$
1[$
0P$
0V$
#52
0^#
0_#
#53
0O#
0V#
b1001 /#
b1001 a#
0*#
0)#
0m#
0l#
#54
0`#
0X#
0Y#
0[$
0\$
b10000010000111 #
b10000010000111 *
b10 ,#
1L#
b10000010000111 !
b10000010000111 s#
1Q$
#100
0Z"
0^"
0o"
0v"
14#
18#
1F#
1M#
b11 H"
b1111 &#
0:$
0@$
1L$
1R$
b1111001111111111 %
b1111001111111111 (
b1111001111111111 b#
#101
0]"
b11 O"
b11 ~"
0a"
0t"
0{"
17#
b1111 -#
b1111 \#
1;#
1K#
0>$
0D$
1P$
#102
0##
0$#
1^#
#103
0x"
0+
1O#
b11 Q"
b11 %#
b1011 /#
b1011 a#
0K"
0J"
1*#
0p#
0o#
1m#
#104
0D#
0]#
1_#
1R#
0J$
1V$
b100 N"
1u"
b10010000111 #
b10010000111 *
b0 ,#
0L#
1?$
b10010000111 !
b10010000111 s#
0Q$
#105
0H#
1V#
b1110 /#
b1110 a#
#106
0^#
0K#
1`#
1X#
1Y#
0+#
1)#
0n#
1l#
#107
0O#
b1100 /#
b1100 a#
0P$
1[$
1\$
b1010010000111 #
b1010010000111 *
b1 ,#
1E#
b1010010000111 !
b1010010000111 s#
1K$
#108
0_#
0R#
0*#
#109
0V#
b1000 /#
b1000 a#
0m#
1L#
b1011010010000111 #
b1011010010000111 *
b1011 ,#
1Z#
#110
0`#
0X#
0Y#
0V$
0)#
1Q$
b1011010010000111 !
b1011010010000111 s#
1]$
#111
b1111010010000111 #
b1111010010000111 *
b1111 ,#
1S#
#112
0l#
#113
0[$
0\$
b111010010000111 #
b111010010000111 *
b111 ,#
0Z#
b1111010010000111 !
b1111010010000111 s#
1W$
#116
b111010010000111 !
b111010010000111 s#
0]$
#150
0D
0\
0t
0&"
1Z"
1^"
1o"
1v"
b111 .
b1110 j
b1111 H"
0p$
0t#
1:$
1@$
b1111111111100111 %
b1111111111100111 (
b1111111111100111 b#
#151
b0 6
b0 c
0F
0_
b1110 q
b1110 B"
0w
0*"
1]"
b1111 O"
b1111 ~"
1a"
1t"
0r$
0x#
1>$
#152
0-
b0 7
b0 i
0C"
1##
#153
0."
1x"
b1110 s
b1110 G"
b111 Q"
b111 %#
00
0o
1K"
0i#
0h#
1p#
#154
0D"
01"
1$#
1{"
0~#
1D$
b1111 4
1b
b111000010001111 #
b111000010001111 *
b0 N"
0u"
1u$
b111000010001111 !
b111000010001111 s#
0?$
#155
05"
1+
b1100 s
b1100 G"
b1111 Q"
b1111 %#
#156
0E"
08"
1D#
1]#
0n
1J"
0g#
1o#
#157
0<"
1H#
b1000 s
b1000 G"
b1001 /#
b1001 a#
0&$
1J$
b111000010101111 #
b111000010101111 *
b1010 p
12"
b111000010101111 !
b111000010101111 s#
1!$
#158
0F"
0>"
0?"
1^#
1K#
0m
1+#
#159
1O#
b1011 /#
b1011 a#
0f#
1n#
b1110 p
19"
b110000011101111 #
b110000011101111 *
b110 ,#
0E#
#160
1_#
1R#
0+$
0,$
1P$
1*#
1'$
b110000011101111 !
b110000011101111 s#
0K$
#161
1V#
b1111 /#
b1111 a#
b110 p
0@"
b100000001101111 #
b100000001101111 *
b100 ,#
0L#
#162
1`#
1X#
1Y#
1)#
1m#
#163
1V$
b1101111 #
b1101111 *
b0 ,#
0S#
0-$
b100000001101111 !
b100000001101111 s#
0Q$
#165
1l#
b1000000001101111 #
b1000000001101111 *
b1000 ,#
1Z#
#166
1[$
1\$
b1101111 !
b1101111 s#
0W$
#169
b1000000001101111 !
b1000000001101111 s#
1]$
