Lab6/FPGA.v
// Code your design here
module logic_tile(out, clock, in1, in2, in3, in4, in5);
	input clock, in1, in2, in3, in4, in5 ;
  output out;
  reg [32:0] mem;
  reg  q, qbar;
  wire d;
  initial
      begin
      q=1'b0;
      end

  assign d=mem[{in5,in4,in3,in2,in1}];
  
  	
	always@(posedge clock) 
	begin
      q <= d; 
      qbar = !d; 
	end
	

  assign out=(q & mem[32])|(d & ~mem[32]);


endmodule


module switch_box_4x4(out, in);
  input [3:0] in;
  output [3:0] out;
  reg [15:0] configure;
  
  assign out[0] =  ((configure[0]&in[0]) | (in[1] & configure[1]) | (configure[2] & in[2]) | (in[3] & configure[3])); 
  assign out[1] =  ((configure[4]&in[0]) | (in[1] & configure[5]) | (configure[6] & in[2]) | (in[3] & configure[7]));
  assign out[2] =  ((configure[8]&in[0]) | (in[1] & configure[9]) | (configure[10] & in[2]) | (in[3] & configure[11]));
  assign out[3] =  ((configure[12]&in[0]) | (in[1] & configure[13]) | (configure[14] & in[2]) | (in[3] & configure[15]));
  
endmodule


module lab6_2circuits(A,B,cin,sum,cout,E,F,clock);
  input clock;
  input [3:0] A;
  input [3:0] B;
  input cin;
  output [3:0] sum;
  output cout;
  wire [3:0] SUM;
  wire cout0,cout1,cout2,cout3,cout4;
  input [7:0] E;
  output [2:0] F;
  
  
  
  logic_tile ins1(.out(SUM[0]), .clock(clock), .in1(cin), .in2(B[0]), .in3(A[0]),.in4(1'b0), .in5(1'b0));
  logic_tile ins2(.out(cout0), .clock(clock), .in1(cin), .in2(B[0]), .in3(A[0]),.in4(1'b0), .in5(1'b0));
  
  
  logic_tile ins3(.out(SUM[1]), .clock(clock), .in1(cout0), .in2(B[1]), .in3(A[1]),.in4(1'b0), .in5(1'b0));
 
  logic_tile ins4(.out(cout1), .clock(clock), .in1(cout0), .in2(B[1]), .in3(A[1]),.in4(1'b0), .in5(1'b0));
  
 
  logic_tile ins5(.out(SUM[2]), .clock(clock), .in1(cout1), .in2(B[2]), .in3(A[2]),.in4(1'b0), .in5(1'b0));
  logic_tile ins6(.out(cout2), .clock(clock), .in1(cout1), .in2(B[2]), .in3(A[2]),.in4(1'b0), .in5(1'b0));
  
  
  logic_tile ins7(.out(SUM[3]), .clock(clock), .in1(cout2), .in2(B[3]), .in3(A[3]),.in4(1'b0), .in5(1'b0));
  logic_tile ins8(.out(cout3), .clock(clock), .in1(cout2), .in2(B[3]),  .in3(A[3]) ,.in4(1'b0), .in5(1'b0));
   
  
  logic_tile ins9(.out(cout), .clock(clock), .in1(SUM[0]),.in2(SUM[1]), .in3(SUM[2]), .in4(SUM[3]), .in5(cout3));
  
  logic_tile ins10(.out(sum[0]), .clock(clock), .in1(SUM[0]),.in2(SUM[1]), .in3(SUM[2]), .in4(SUM[3]), .in5(cout3));
  
  logic_tile ins11(.out(sum[1]), .clock(clock), .in1(SUM[0]),.in2(SUM[1]), .in3(SUM[2]), .in4(SUM[3]), .in5(cout3));
  
  logic_tile ins12(.out(sum[2]), .clock(clock), .in1(SUM[0]),.in2(SUM[1]), .in3(SUM[2]), .in4(SUM[3]), .in5(cout3));
  
  logic_tile ins13(.out(sum[3]), .clock(clock), .in1(SUM[0]),.in2(SUM[1]), .in3(SUM[2]), .in4(SUM[3]), .in5(cout3));
  
  logic_tile inst1(.out(F[2]), .clock(clock), .in1(E[4]),.in2(E[5]), .in3(E[6]), .in4(E[7]), .in5(1'b0));
  
  logic_tile inst2(.out(F[1]), .clock(clock), .in1(E[2]),.in2(E[3]), .in3(E[6]), .in4(E[7]), .in5(1'b0));
  
  logic_tile inst3(.out(F[0]), .clock(clock), .in1(E[1]),.in2(E[3]), .in3(E[5]), .in4(E[7]), .in5(1'b0));

  
  
endmodule

Lab6/testbench_enc.v
// Code your testbench here
// or browse Examples
module enc_tb();
  reg [3:0] tb_A=4'b0000;
  reg [3:0] tb_B=4'b0000;
  reg tb_cin=1'b0;
  wire [3:0] tb_sum=4'b0000;
  wire tb_cout=4'b0000;
  reg [7:0] tb_E;
  wire [2:0] tb_F;
  reg clk;
  initial clk = 0; 
  always #10 clk = ~clk;
  
  reg [31:0] tb_mem [0:2];
   lab6_2circuits enc_ins(.A(tb_A),.B(tb_B),.cin(tb_cin),.sum(tb_sum),.cout(tb_cout),.E(tb_E),.F(tb_F),.clock(clk));
  initial
    begin
      $readmemh("configure8_to_3encoder.mem",tb_mem);
      enc_ins.inst1.mem[31:0]=tb_mem[0];
      enc_ins.inst1.mem[32]=tb_mem[1];
      enc_ins.inst2.mem[31:0]=tb_mem[0];
      enc_ins.inst2.mem[32]=tb_mem[1];
      
      enc_ins.inst3.mem[31:0]=tb_mem[0];
      enc_ins.inst3.mem[32]=tb_mem[1];
      
      
      tb_E=8'b00010000;
      
      #20
      $display("8 to 3 encoder::  E= %b ,F= %b",tb_E,tb_F);
      
      tb_E=8'b00001000;
      
      #20
      $display("8 to 3 encoder::  E= %b ,F= %b",tb_E,tb_F);
      
      tb_E=8'b00000010;
      
      #20
      $display("8 to 3 encoder::  E= %b ,F= %b",tb_E,tb_F);
      
      tb_E=8'b00000001;
      
      #20
      $display("8 to 3 encoder::  E= %b ,F= %b",tb_E,tb_F);
      
      
      
      
      
      
    end
  
  initial 
      #1000 $finish;
  
  	initial
    begin
      $dumpfile("2019csb1100_enc.vcd");
      $dumpvars;
      
    end 
  
  

endmodule

Lab6/2019csb1100_enc.vcd
$date
	Wed Nov 25 03:57:46 2020
$end
$version
	Icarus Verilog
$end
$timescale
	1s
$end
$scope module enc_tb $end
$var wire 1 ! tb_cout $end
$var wire 4 " tb_sum [3:0] $end
$var wire 3 # tb_F [2:0] $end
$var reg 1 $ clk $end
$var reg 4 % tb_A [3:0] $end
$var reg 4 & tb_B [3:0] $end
$var reg 8 ' tb_E [7:0] $end
$var reg 1 ( tb_cin $end
$scope module enc_ins $end
$var wire 4 ) A [3:0] $end
$var wire 4 * B [3:0] $end
$var wire 8 + E [7:0] $end
$var wire 1 ( cin $end
$var wire 1 $ clock $end
$var wire 1 ! cout $end
$var wire 4 , sum [3:0] $end
$var wire 1 - cout3 $end
$var wire 1 . cout2 $end
$var wire 1 / cout1 $end
$var wire 1 0 cout0 $end
$var wire 4 1 SUM [3:0] $end
$var wire 3 2 F [2:0] $end
$scope module ins1 $end
$var wire 1 $ clock $end
$var wire 1 ( in1 $end
$var wire 1 3 in2 $end
$var wire 1 4 in3 $end
$var wire 1 5 in4 $end
$var wire 1 6 in5 $end
$var wire 1 7 out $end
$var wire 1 8 d $end
$var reg 33 9 mem [32:0] $end
$var reg 1 : q $end
$var reg 1 ; qbar $end
$upscope $end
$scope module ins10 $end
$var wire 1 $ clock $end
$var wire 1 < in1 $end
$var wire 1 = in2 $end
$var wire 1 > in3 $end
$var wire 1 ? in4 $end
$var wire 1 @ out $end
$var wire 1 - in5 $end
$var wire 1 A d $end
$var reg 33 B mem [32:0] $end
$var reg 1 C q $end
$var reg 1 D qbar $end
$upscope $end
$scope module ins11 $end
$var wire 1 $ clock $end
$var wire 1 E in1 $end
$var wire 1 F in2 $end
$var wire 1 G in3 $end
$var wire 1 H in4 $end
$var wire 1 I out $end
$var wire 1 - in5 $end
$var wire 1 J d $end
$var reg 33 K mem [32:0] $end
$var reg 1 L q $end
$var reg 1 M qbar $end
$upscope $end
$scope module ins12 $end
$var wire 1 $ clock $end
$var wire 1 N in1 $end
$var wire 1 O in2 $end
$var wire 1 P in3 $end
$var wire 1 Q in4 $end
$var wire 1 R out $end
$var wire 1 - in5 $end
$var wire 1 S d $end
$var reg 33 T mem [32:0] $end
$var reg 1 U q $end
$var reg 1 V qbar $end
$upscope $end
$scope module ins13 $end
$var wire 1 $ clock $end
$var wire 1 W in1 $end
$var wire 1 X in2 $end
$var wire 1 Y in3 $end
$var wire 1 Z in4 $end
$var wire 1 [ out $end
$var wire 1 - in5 $end
$var wire 1 \ d $end
$var reg 33 ] mem [32:0] $end
$var reg 1 ^ q $end
$var reg 1 _ qbar $end
$upscope $end
$scope module ins2 $end
$var wire 1 $ clock $end
$var wire 1 ( in1 $end
$var wire 1 ` in2 $end
$var wire 1 a in3 $end
$var wire 1 b in4 $end
$var wire 1 c in5 $end
$var wire 1 0 out $end
$var wire 1 d d $end
$var reg 33 e mem [32:0] $end
$var reg 1 f q $end
$var reg 1 g qbar $end
$upscope $end
$scope module ins3 $end
$var wire 1 $ clock $end
$var wire 1 0 in1 $end
$var wire 1 h in2 $end
$var wire 1 i in3 $end
$var wire 1 j in4 $end
$var wire 1 k in5 $end
$var wire 1 l out $end
$var wire 1 m d $end
$var reg 33 n mem [32:0] $end
$var reg 1 o q $end
$var reg 1 p qbar $end
$upscope $end
$scope module ins4 $end
$var wire 1 $ clock $end
$var wire 1 0 in1 $end
$var wire 1 q in2 $end
$var wire 1 r in3 $end
$var wire 1 s in4 $end
$var wire 1 t in5 $end
$var wire 1 / out $end
$var wire 1 u d $end
$var reg 33 v mem [32:0] $end
$var reg 1 w q $end
$var reg 1 x qbar $end
$upscope $end
$scope module ins5 $end
$var wire 1 $ clock $end
$var wire 1 / in1 $end
$var wire 1 y in2 $end
$var wire 1 z in3 $end
$var wire 1 { in4 $end
$var wire 1 | in5 $end
$var wire 1 } out $end
$var wire 1 ~ d $end
$var reg 33 !" mem [32:0] $end
$var reg 1 "" q $end
$var reg 1 #" qbar $end
$upscope $end
$scope module ins6 $end
$var wire 1 $ clock $end
$var wire 1 / in1 $end
$var wire 1 $" in2 $end
$var wire 1 %" in3 $end
$var wire 1 &" in4 $end
$var wire 1 '" in5 $end
$var wire 1 . out $end
$var wire 1 (" d $end
$var reg 33 )" mem [32:0] $end
$var reg 1 *" q $end
$var reg 1 +" qbar $end
$upscope $end
$scope module ins7 $end
$var wire 1 $ clock $end
$var wire 1 . in1 $end
$var wire 1 ," in2 $end
$var wire 1 -" in3 $end
$var wire 1 ." in4 $end
$var wire 1 /" in5 $end
$var wire 1 0" out $end
$var wire 1 1" d $end
$var reg 33 2" mem [32:0] $end
$var reg 1 3" q $end
$var reg 1 4" qbar $end
$upscope $end
$scope module ins8 $end
$var wire 1 $ clock $end
$var wire 1 . in1 $end
$var wire 1 5" in2 $end
$var wire 1 6" in3 $end
$var wire 1 7" in4 $end
$var wire 1 8" in5 $end
$var wire 1 - out $end
$var wire 1 9" d $end
$var reg 33 :" mem [32:0] $end
$var reg 1 ;" q $end
$var reg 1 <" qbar $end
$upscope $end
$scope module ins9 $end
$var wire 1 $ clock $end
$var wire 1 =" in1 $end
$var wire 1 >" in2 $end
$var wire 1 ?" in3 $end
$var wire 1 @" in4 $end
$var wire 1 - in5 $end
$var wire 1 ! out $end
$var wire 1 A" d $end
$var reg 33 B" mem [32:0] $end
$var reg 1 C" q $end
$var reg 1 D" qbar $end
$upscope $end
$scope module inst1 $end
$var wire 1 $ clock $end
$var wire 1 E" in1 $end
$var wire 1 F" in2 $end
$var wire 1 G" in3 $end
$var wire 1 H" in4 $end
$var wire 1 I" in5 $end
$var wire 1 J" out $end
$var wire 1 K" d $end
$var reg 33 L" mem [32:0] $end
$var reg 1 M" q $end
$var reg 1 N" qbar $end
$upscope $end
$scope module inst2 $end
$var wire 1 $ clock $end
$var wire 1 O" in1 $end
$var wire 1 P" in2 $end
$var wire 1 Q" in3 $end
$var wire 1 R" in4 $end
$var wire 1 S" in5 $end
$var wire 1 T" out $end
$var wire 1 U" d $end
$var reg 33 V" mem [32:0] $end
$var reg 1 W" q $end
$var reg 1 X" qbar $end
$upscope $end
$scope module inst3 $end
$var wire 1 $ clock $end
$var wire 1 Y" in1 $end
$var wire 1 Z" in2 $end
$var wire 1 [" in3 $end
$var wire 1 \" in4 $end
$var wire 1 ]" in5 $end
$var wire 1 ^" out $end
$var wire 1 _" d $end
$var reg 33 `" mem [32:0] $end
$var reg 1 a" q $end
$var reg 1 b" qbar $end
$upscope $end
$upscope $end
$upscope $end
$scope module switch_box_4x4 $end
$var wire 4 c" in [3:0] $end
$var wire 4 d" out [3:0] $end
$var reg 16 e" configure [15:0] $end
$upscope $end
$enddefinitions $end
#0
$dumpvars
bx e"
bx d"
bz c"
xb"
0a"
b100010110 `"
0_"
0^"
0]"
0\"
0["
0Z"
0Y"
xX"
0W"
b100010110 V"
0U"
0T"
0S"
0R"
0Q"
0P"
0O"
xN"
0M"
b100010110 L"
1K"
1J"
0I"
0H"
0G"
0F"
1E"
xD"
0C"
bx B"
xA"
x@"
x?"
x>"
x="
x<"
0;"
bx :"
x9"
08"
07"
06"
05"
x4"
03"
bx 2"
x1"
x0"
0/"
0."
0-"
0,"
x+"
0*"
bx )"
x("
0'"
0&"
0%"
0$"
x#"
0""
bx !"
x~
x}
0|
0{
0z
0y
xx
0w
bx v
xu
0t
0s
0r
0q
xp
0o
bx n
xm
xl
0k
0j
0i
0h
xg
0f
bx e
xd
0c
0b
0a
0`
x_
0^
bx ]
x\
x[
xZ
xY
xX
xW
xV
0U
bx T
xS
xR
xQ
xP
xO
xN
xM
0L
bx K
xJ
xI
xH
xG
xF
xE
xD
0C
bx B
xA
x@
x?
x>
x=
x<
x;
0:
bx 9
x8
x7
06
05
04
03
b100 2
bx 1
x0
x/
x.
x-
bx ,
b10000 +
b0 *
b0 )
0(
b10000 '
b0 &
b0 %
0$
b100 #
bx "
x!
$end
#10
x:
xf
xo
xw
x""
x*"
x3"
x;"
xC"
xC
xL
xU
x^
1M"
0N"
1X"
1b"
1$
#20
0J"
1T"
b11 #
b11 2
1^"
0K"
0E"
1U"
1P"
1_"
1Z"
0$
b1000 '
b1000 +
#30
1a"
1W"
0M"
0b"
0X"
1N"
1$
#40
b1 #
b1 2
0T"
0U"
0P"
1Y"
1_"
0Z"
0$
b10 '
b10 +
#50
0W"
1X"
1$
#60
b0 #
b0 2
0^"
0_"
0Y"
0$
b1 '
b1 +
#70
0a"
1b"
1$
